[
  {
    "time": "2026-06-17T14:07:30.959568Z",
    "level": "INFO",
    "event": "login_start",
    "message": "Attempting ERP login"
  },
  {
    "time": "2026-06-17T14:07:36.610066Z",
    "level": "INFO",
    "event": "login_success",
    "message": "ERP login successful"
  },
  {
    "time": "2026-06-17T14:07:36.610081Z",
    "level": "INFO",
    "event": "fetch_subjects",
    "message": "Fetching LMS dashboard"
  },
  {
    "time": "2026-06-17T14:07:37.155710Z",
    "level": "INFO",
    "event": "subjects_found",
    "message": "7 subjects found"
  },
  {
    "time": "2026-06-17T14:07:42.716424Z",
    "level": "INFO",
    "event": "assignments_extracted",
    "message": "Assignments extracted",
    "extra": {
      "subject": "SECE4060 - Artificial Inteligence of Things",
      "count": 11
    }
  },
  {
    "time": "2026-06-17T14:07:42.799508Z",
    "level": "INFO",
    "event": "assignments_extracted",
    "message": "Assignments extracted",
    "extra": {
      "subject": "SECE4070 - Computer Vision",
      "count": 12
    }
  },
  {
    "time": "2026-06-17T14:07:42.872097Z",
    "level": "INFO",
    "event": "assignments_extracted",
    "message": "Assignments extracted",
    "extra": {
      "subject": "SECE4080 - Natural Language Processing",
      "count": 12
    }
  },
  {
    "time": "2026-06-17T14:07:42.976693Z",
    "level": "INFO",
    "event": "json_written",
    "message": "assignments.json written",
    "extra": {
      "count": 26
    }
  }
]